<?xml version="1.0" encoding="utf-8" ?><dwsync><file name="EyeRecruit_Avitar.jpg" server="198.46.81.222/public_html/demo/" local="3575571449" remote="319783739209457608" Dst="-1" /><file name="Pre-Recorded-Interviews.jpg" server="198.46.81.222/public_html/demo/" local="3575571450" remote="319783739215866148" Dst="-1" /><file name="Slide07.jpg" server="198.46.81.222/public_html/demo/" local="3575571450" remote="319783739203041088" Dst="-1" /><file name="ata_glance.jpg" server="198.46.81.222/public_html/demo/" local="3575571450" remote="319783739215866148" Dst="-1" /><file name="ad1.jpg" server="198.46.81.222/public_html/demo/" local="3575571450" remote="319783739203041088" Dst="-1" /><file name="ad4.jpg" server="198.46.81.222/public_html/demo/" local="3575571450" remote="319783739203041088" Dst="-1" /><file name="awarded_badge1.jpg" server="198.46.81.222/public_html/demo/" local="3575571450" remote="319783739215866148" Dst="-1" /><file name="awarded_badge2.jpg" server="198.46.81.222/public_html/demo/" local="3575571450" remote="319783739215866148" Dst="-1" /><file name="awarded_badge4.jpg" server="198.46.81.222/public_html/demo/" local="3575571450" remote="319783739215866148" Dst="-1" /><file name="backcheck.jpg" server="198.46.81.222/public_html/demo/" local="3575571450" remote="319783739204229028" Dst="-1" /><file name="awarded_badge3.jpg" server="198.46.81.222/public_html/demo/" local="3575571450" remote="319783739215866148" Dst="-1" /><file name="barkleysecurity.png" server="198.46.81.222/public_html/demo/" local="3575571451" remote="319783739203041088" Dst="-1" /><file name="big_minus.jpg" server="198.46.81.222/public_html/demo/" local="3575571451" remote="319783739215866148" Dst="-1" /><file name="blocked_img.png" server="198.46.81.222/public_html/demo/" local="3575571451" remote="319783739211366928" Dst="-1" /><file name="blogslider_img.jpg" server="198.46.81.222/public_html/demo/" local="3575571451" remote="319783739203041088" Dst="-1" /><file name="cirstopher_sign.jpg" server="198.46.81.222/public_html/demo/" local="3575571451" remote="319783739203041088" Dst="-1" /><file name="clearance_icon.png" server="198.46.81.222/public_html/demo/" local="3575571451" remote="319783739215866148" Dst="-1" /><file name="cirstopher.jpg" server="198.46.81.222/public_html/demo/" local="3575571451" remote="319783739203041088" Dst="-1" /><file name="coverletter_logoicon.jpg" server="198.46.81.222/public_html/demo/" local="3575571451" remote="319783739205999208" Dst="-1" /><file name="coming_soon.jpg" server="198.46.81.222/public_html/demo/" local="3575571451" remote="319783739209464508" Dst="-1" /><file name="emoji.jpg" server="198.46.81.222/public_html/demo/" local="3575571452" remote="319783739203041088" Dst="-1" /><file name="coverletter_name.png" server="198.46.81.222/public_html/demo/" local="3575571452" remote="319783739205999208" Dst="-1" /><file name="coverletter.jpg" server="198.46.81.222/public_html/demo/" local="3575571452" remote="319783739203041088" Dst="-1" /><file name="employer1.jpg" server="198.46.81.222/public_html/demo/" local="3575571452" remote="319783739203041088" Dst="-1" /><file name="employer2.jpg" server="198.46.81.222/public_html/demo/" local="3575571452" remote="319783739203041088" Dst="-1" /><file name="employer3.jpg" server="198.46.81.222/public_html/demo/" local="3575571452" remote="319783739203041088" Dst="-1" /><file name="employer4.jpg" server="198.46.81.222/public_html/demo/" local="3575571452" remote="319783739203041088" Dst="-1" /><file name="employer5.jpg" server="198.46.81.222/public_html/demo/" local="3575571452" remote="319783739203041088" Dst="-1" /><file name="employer6.jpg" server="198.46.81.222/public_html/demo/" local="3575571453" remote="319783739203041088" Dst="-1" /><file name="employer_default.jpg" server="198.46.81.222/public_html/demo/" local="3575571453" remote="319783739204229808" Dst="-1" /><file name="enforcement_icon.jpg" server="198.46.81.222/public_html/demo/" local="3575571453" remote="319783739215866148" Dst="-1" /><file name="eyerecruit-torch-far.jpg" server="198.46.81.222/public_html/demo/" local="3575571453" remote="319783739215254928" Dst="-1" /><file name="error-404.png" server="198.46.81.222/public_html/demo/" local="3575571453" remote="319783739211374248" Dst="-1" /><file name="eyerecruit_circle.png" server="198.46.81.222/public_html/demo/" local="3575571453" remote="319783739214645808" Dst="-1" /><file name="eyerecruit_squire.jpg" server="198.46.81.222/public_html/demo/" local="3575571453" remote="319783739215494628" Dst="-1" /><file name="federal_shield.jpg" server="198.46.81.222/public_html/demo/" local="3575571453" remote="319783739215866148" Dst="-1" /><file name="facebook.png" server="198.46.81.222/public_html/demo/" local="3575571453" remote="319783739203041088" Dst="-1" /><file name="featured_spotlight_icon.jpg" server="198.46.81.222/public_html/demo/" local="3575571453" remote="319783739215866148" Dst="-1" /><file name="gray_bg.jpg" server="198.46.81.222/public_html/demo/" local="3575571454" remote="319783739205999208" Dst="-1" /><file name="filter_icon.png" server="198.46.81.222/public_html/demo/" local="3575571454" remote="319783739215254928" Dst="-1" /><file name="galls-security-enforcement-officer-badge-at-galls-NFtP3y-clipart.JPG" server="198.46.81.222/public_html/demo/" local="3575571454" remote="319783739203473088" Dst="-1" /><file name="graylock_sm.png" server="198.46.81.222/public_html/demo/" local="3575571454" remote="319783739215866148" Dst="-1" /><file name="green_checklg.jpg" server="198.46.81.222/public_html/demo/" local="3575571454" remote="319783739206604548" Dst="-1" /><file name="jobdetail_logo.jpg" server="198.46.81.222/public_html/demo/" local="3575571454" remote="319783739203473088" Dst="-1" /><file name="icon-eye-magnifying-glass.png" server="198.46.81.222/public_html/demo/" local="3575571454" remote="319783739217329008" Dst="-1" /><file name="like_icons.png" server="198.46.81.222/public_html/demo/" local="3575571454" remote="319783739205397048" Dst="-1" /><file name="job_posting_seeker_view.jpg" server="198.46.81.222/public_html/demo/" local="3575571455" remote="319783739204374108" Dst="-1" /><file name="linkedin.png" server="198.46.81.222/public_html/demo/" local="3575571455" remote="319783739203041088" Dst="-1" /><file name="list-img.jpg" server="198.46.81.222/public_html/demo/" local="3575571455" remote="319783739215071388" Dst="-1" /><file name="leftside_ad.jpg" server="198.46.81.222/public_html/demo/" local="3575571455" remote="319783739215866148" Dst="-1" /><file name="lock.jpg" server="198.46.81.222/public_html/demo/" local="3575571455" remote="319783739211974068" Dst="-1" /><file name="lock_sm.png" server="198.46.81.222/public_html/demo/" local="3575571455" remote="319783739212571968" Dst="-1" /><file name="logo.jpg" server="198.46.81.222/public_html/demo/" local="3575571455" remote="319783739218011808" Dst="-1" /><file name="logo.png" server="198.46.81.222/public_html/demo/" local="3575571455" remote="319783739203041088" Dst="-1" /><file name="logo_cop.png" server="198.46.81.222/public_html/demo/" local="3575571455" remote="319783739217502408" Dst="-1" /><file name="map_marker.png" server="198.46.81.222/public_html/demo/" local="3575571457" remote="319783739203041088" Dst="-1" /><file name="message_icon.jpg" server="198.46.81.222/public_html/demo/" local="3575571457" remote="319783739213189428" Dst="-1" /><file name="map_marker_sm.png" server="198.46.81.222/public_html/demo/" local="3575571457" remote="319783739203041088" Dst="-1" /><file name="maritime.png" server="198.46.81.222/public_html/demo/" local="3575571457" remote="319783739208612928" Dst="-1" /><file name="military_service_icon.png" server="198.46.81.222/public_html/demo/" local="3575571457" remote="319783739215866148" Dst="-1" /><file name="mini_torch.png" server="198.46.81.222/public_html/demo/" local="3575571457" remote="319783739203041088" Dst="-1" /><file name="miamisecurity.png" server="198.46.81.222/public_html/demo/" local="3575571457" remote="319783739203041088" Dst="-1" /><file name="navi_logo-icon.png" server="198.46.81.222/public_html/demo/" local="3575571457" remote="319783739211347488" Dst="-1" /><file name="navback_manage.jpg" server="198.46.81.222/public_html/demo/" local="3575571457" remote="319783739209805668" Dst="-1" /><file name="navigation_icons.png" server="198.46.81.222/public_html/demo/" local="3575571458" remote="319783739204136808" Dst="-1" /><file name="pass-bg.jpg" server="198.46.81.222/public_html/demo/" local="3575571458" remote="319783739211974068" Dst="-1" /><file name="preview_img.jpg" server="198.46.81.222/public_html/demo/" local="3575571458" remote="319783739217332908" Dst="-1" /><file name="preview_img2.jpg" server="198.46.81.222/public_html/demo/" local="3575571458" remote="319783739217332908" Dst="-1" /><file name="prices_lock.png" server="198.46.81.222/public_html/demo/" local="3575571458" remote="319783739209725208" Dst="-1" /><file name="pricing_listicon.png" server="198.46.81.222/public_html/demo/" local="3575571458" remote="319783739205397048" Dst="-1" /><file name="pagetitle_bg.jpg" server="198.46.81.222/public_html/demo/" local="3575571458" remote="319783739203041088" Dst="-1" /><file name="pricing_logo.png" server="198.46.81.222/public_html/demo/" local="3575571459" remote="319783739205397048" Dst="-1" /><file name="profile-img.png" server="198.46.81.222/public_html/demo/" local="3575571459" remote="319783739208612928" Dst="-1" /><file name="profile_badge.jpg" server="198.46.81.222/public_html/demo/" local="3575571459" remote="319783739209555108" Dst="-1" /><file name="profile_badge.png" server="198.46.81.222/public_html/demo/" local="3575571459" remote="319783739209555108" Dst="-1" /><file name="quick_farward_icon.jpg" server="198.46.81.222/public_html/demo/" local="3575571459" remote="319783739215866148" Dst="-1" /><file name="recruiter_img.jpg" server="198.46.81.222/public_html/demo/" local="3575571459" remote="319783739203041088" Dst="-1" /><file name="rgister_member.jpg" server="198.46.81.222/public_html/demo/" local="3575571459" remote="319783739215494628" Dst="-1" /><file name="refer_bg.jpg" server="198.46.81.222/public_html/demo/" local="3575571459" remote="319783739203041088" Dst="-1" /><file name="rightside_ad.jpg" server="198.46.81.222/public_html/demo/" local="3575571460" remote="319783739215866148" Dst="-1" /><file name="sa1084_1.jpg" server="198.46.81.222/public_html/demo/" local="3575571460" remote="319783739203473088" Dst="-1" /><file name="security_officer.jpg" server="198.46.81.222/public_html/demo/" local="3575571460" remote="319783739203473088" Dst="-1" /><file name="security_pro_img.jpg" server="198.46.81.222/public_html/demo/" local="3575571460" remote="319783739205999208" Dst="-1" /><file name="seeker_basicicon.jpg" server="198.46.81.222/public_html/demo/" local="3575571460" remote="319783739205397048" Dst="-1" /><file name="seeker_plusicon.jpg" server="198.46.81.222/public_html/demo/" local="3575571460" remote="319783739205397048" Dst="-1" /><file name="seeker_premiumicon.jpg" server="198.46.81.222/public_html/demo/" local="3575571460" remote="319783739205397048" Dst="-1" /><file name="seeker_ultimateicon.jpg" server="198.46.81.222/public_html/demo/" local="3575571460" remote="319783739205397048" Dst="-1" /><file name="side_assessments_icons.png" server="198.46.81.222/public_html/demo/" local="3575571460" remote="319783739204150548" Dst="-1" /><file name="sprofile_icons.png" server="198.46.81.222/public_html/demo/" local="3575571461" remote="319783739203041088" Dst="-1" /><file name="speciallogo.jpg" server="198.46.81.222/public_html/demo/" local="3575571461" remote="319783739203041088" Dst="-1" /><file name="sprofile_logo.jpg" server="198.46.81.222/public_html/demo/" local="3575571461" remote="319783739203041088" Dst="-1" /><file name="sprofile_user.jpg" server="198.46.81.222/public_html/demo/" local="3575571461" remote="319783739203041088" Dst="-1" /><file name="seeker_map.jpg" server="198.46.81.222/public_html/demo/" local="3575571461" remote="319783739203041088" Dst="-1" /><file name="star_b.png" server="198.46.81.222/public_html/demo/" local="3575571461" remote="319783739203041088" Dst="-1" /><file name="star_r.png" server="198.46.81.222/public_html/demo/" local="3575571461" remote="319783739203041088" Dst="-1" /><file name="survey_result.jpg" server="198.46.81.222/public_html/demo/" local="3575571461" remote="319783739210133268" Dst="-1" /><file name="team_member1.jpg" server="198.46.81.222/public_html/demo/" local="3575571461" remote="319783739205397048" Dst="-1" /><file name="team_member3.jpg" server="198.46.81.222/public_html/demo/" local="3575571462" remote="319783739205397048" Dst="-1" /><file name="team_member2.jpg" server="198.46.81.222/public_html/demo/" local="3575571462" remote="319783739205397048" Dst="-1" /><file name="title_icons.png" server="198.46.81.222/public_html/demo/" local="3575571462" remote="319783739205397048" Dst="-1" /><file name="tourch_md.jpg" server="198.46.81.222/public_html/demo/" local="3575571462" remote="319783739215866148" Dst="-1" /><file name="title_icons_bkp.png" server="198.46.81.222/public_html/demo/" local="3575571462" remote="319783739203041088" Dst="-1" /><file name="twitter.png" server="198.46.81.222/public_html/demo/" local="3575571462" remote="319783739203041088" Dst="-1" /><file name="upload_icons.png" server="198.46.81.222/public_html/demo/" local="3575571462" remote="319783739204291068" Dst="-1" /><file name="upgrades_ending.jpg" server="198.46.81.222/public_html/demo/" local="3575571462" remote="319783739215262008" Dst="-1" /><file name="user3.jpg" server="198.46.81.222/public_html/demo/" local="3575571462" remote="319783739203041088" Dst="-1" /><file name="user2.jpg" server="198.46.81.222/public_html/demo/" local="3575571462" remote="319783739203041088" Dst="-1" /><file name="user1.jpg" server="198.46.81.222/public_html/demo/" local="3575571463" remote="319783739203041088" Dst="-1" /><file name="user4.jpg" server="198.46.81.222/public_html/demo/" local="3575571463" remote="319783739203041088" Dst="-1" /><file name="user5.jpg" server="198.46.81.222/public_html/demo/" local="3575571463" remote="319783739203041088" Dst="-1" /><file name="user6.jpg" server="198.46.81.222/public_html/demo/" local="3575571463" remote="319783739203041088" Dst="-1" /><file name="userprofile.jpg" server="198.46.81.222/public_html/demo/" local="3575571463" remote="319783739203041088" Dst="-1" /><file name="verisign_logo.jpg" server="198.46.81.222/public_html/demo/" local="3575571463" remote="319783739205397048" Dst="-1" /><file name="victig_logo.jpg" server="198.46.81.222/public_html/demo/" local="3575571463" remote="319783739215254928" Dst="-1" /><file name="vic.jpg" server="198.46.81.222/public_html/demo/" local="3575571463" remote="319783739215254928" Dst="-1" /><file name="victig_background_report.jpg" server="198.46.81.222/public_html/demo/" local="3575571463" remote="319783739203041088" Dst="-1" /><file name="video_calender.jpg" server="198.46.81.222/public_html/demo/" local="3575571464" remote="319783739215866148" Dst="-1" /><file name="video_user.jpg" server="198.46.81.222/public_html/demo/" local="3575571464" remote="319783739209555108" Dst="-1" /><file name="video_icon.png" server="198.46.81.222/public_html/demo/" local="3575571464" remote="319783739212236688" Dst="-1" /><file name="visibility_success.jpg" server="198.46.81.222/public_html/demo/" local="3575571464" remote="319783739209446208" Dst="-1" /><file name="welcome_eyerecruit.png" server="198.46.81.222/public_html/demo/" local="3575571464" remote="319783739215254928" Dst="-1" /><file name="youtube.png" server="198.46.81.222/public_html/demo/" local="3575571464" remote="319783739203041088" Dst="-1" /></dwsync>